CHANGELOG.txt
LISCENCE.txt
MANIFEST.in
README.md
main.py
requirements.txt
setup.py
.venv/Lib/site-packages/_virtualenv.py
.venv/Lib/site-packages/BetterPrinting/__init__.py
.venv/Lib/site-packages/BetterPrinting/_main.py
.venv/Lib/site-packages/BetterPrinting/color.py
.venv/Lib/site-packages/BetterPrinting/color_list.py
.venv/Lib/site-packages/BetterPrinting/draw.py
.venv/Lib/site-packages/BetterPrinting/rand.py
.venv/Lib/site-packages/BetterPrinting/system.py
.venv/Lib/site-packages/BetterPrinting/ui.py
.venv/Lib/site-packages/BetterPrinting-0.7.4.dist-info/LICENCE.txt
.venv/Lib/site-packages/BetterPrinting-0.7.4.dist-info/top_level.txt
.venv/Lib/site-packages/PyNaCl-1.5.0.dist-info/top_level.txt
.venv/Lib/site-packages/Pytheas22/Port_Scanner.py
.venv/Lib/site-packages/Pytheas22/Python_Port_Scanner.py
.venv/Lib/site-packages/Pytheas22/__init__.py
.venv/Lib/site-packages/Pytheas22/gui_pytheas.py
.venv/Lib/site-packages/Pytheas22/port_data.py
.venv/Lib/site-packages/Pytheas22-0.1.1.dist-info/LICENSE.txt
.venv/Lib/site-packages/Pytheas22-0.1.1.dist-info/top_level.txt
.venv/Lib/site-packages/_distutils_hack/__init__.py
.venv/Lib/site-packages/_distutils_hack/override.py
.venv/Lib/site-packages/backports/__init__.py
.venv/Lib/site-packages/backports.tarfile-1.2.0.dist-info/top_level.txt
.venv/Lib/site-packages/backports/tarfile/__init__.py
.venv/Lib/site-packages/backports/tarfile/__main__.py
.venv/Lib/site-packages/backports/tarfile/compat/__init__.py
.venv/Lib/site-packages/backports/tarfile/compat/py38.py
.venv/Lib/site-packages/bcrypt/__init__.py
.venv/Lib/site-packages/bcrypt-4.2.0.dist-info/top_level.txt
.venv/Lib/site-packages/certifi/__init__.py
.venv/Lib/site-packages/certifi/__main__.py
.venv/Lib/site-packages/certifi/core.py
.venv/Lib/site-packages/certifi-2024.7.4.dist-info/top_level.txt
.venv/Lib/site-packages/cffi/__init__.py
.venv/Lib/site-packages/cffi/_imp_emulation.py
.venv/Lib/site-packages/cffi/_shimmed_dist_utils.py
.venv/Lib/site-packages/cffi/api.py
.venv/Lib/site-packages/cffi/backend_ctypes.py
.venv/Lib/site-packages/cffi/cffi_opcode.py
.venv/Lib/site-packages/cffi/commontypes.py
.venv/Lib/site-packages/cffi/cparser.py
.venv/Lib/site-packages/cffi/error.py
.venv/Lib/site-packages/cffi/ffiplatform.py
.venv/Lib/site-packages/cffi/lock.py
.venv/Lib/site-packages/cffi/model.py
.venv/Lib/site-packages/cffi/pkgconfig.py
.venv/Lib/site-packages/cffi/recompiler.py
.venv/Lib/site-packages/cffi/setuptools_ext.py
.venv/Lib/site-packages/cffi/vengine_cpy.py
.venv/Lib/site-packages/cffi-1.17.0.dist-info/entry_points.txt
.venv/Lib/site-packages/cffi-1.17.0.dist-info/top_level.txt
.venv/Lib/site-packages/charset_normalizer-3.3.2.dist-info/entry_points.txt
.venv/Lib/site-packages/charset_normalizer-3.3.2.dist-info/top_level.txt
.venv/Lib/site-packages/colorama-0.4.6.dist-info/licenses/LICENSE.txt
.venv/Lib/site-packages/docutils-0.21.2.dist-info/COPYING.txt
.venv/Lib/site-packages/docutils-0.21.2.dist-info/entry_points.txt
.venv/Lib/site-packages/idna-3.7.dist-info/LICENSE.md
.venv/Lib/site-packages/importlib_metadata-8.4.0.dist-info/top_level.txt
.venv/Lib/site-packages/jaraco.classes-3.4.0.dist-info/top_level.txt
.venv/Lib/site-packages/jaraco.context-6.0.1.dist-info/top_level.txt
.venv/Lib/site-packages/jaraco.functools-4.0.2.dist-info/top_level.txt
.venv/Lib/site-packages/keyring-25.3.0.dist-info/entry_points.txt
.venv/Lib/site-packages/keyring-25.3.0.dist-info/top_level.txt
.venv/Lib/site-packages/markdown_it_py-3.0.0.dist-info/entry_points.txt
.venv/Lib/site-packages/paho_mqtt-2.1.0.dist-info/licenses/LICENSE.txt
.venv/Lib/site-packages/paramiko-3.4.1.dist-info/top_level.txt
.venv/Lib/site-packages/pip-23.2.1.dist-info/AUTHORS.txt
.venv/Lib/site-packages/pip-23.2.1.dist-info/LICENSE.txt
.venv/Lib/site-packages/pip-23.2.1.dist-info/entry_points.txt
.venv/Lib/site-packages/pip-23.2.1.dist-info/top_level.txt
.venv/Lib/site-packages/pkginfo-1.10.0.dist-info/LICENSE.txt
.venv/Lib/site-packages/pkginfo-1.10.0.dist-info/entry_points.txt
.venv/Lib/site-packages/pkginfo-1.10.0.dist-info/top_level.txt
.venv/Lib/site-packages/pycparser-2.22.dist-info/top_level.txt
.venv/Lib/site-packages/pygments-2.18.0.dist-info/entry_points.txt
.venv/Lib/site-packages/python_dotenv-1.0.1.dist-info/entry_points.txt
.venv/Lib/site-packages/python_dotenv-1.0.1.dist-info/top_level.txt
.venv/Lib/site-packages/pywin32_ctypes-0.2.3.dist-info/LICENSE.txt
.venv/Lib/site-packages/pywin32_ctypes-0.2.3.dist-info/top_level.txt
.venv/Lib/site-packages/readme_renderer-44.0.dist-info/top_level.txt
.venv/Lib/site-packages/requests-2.32.3.dist-info/top_level.txt
.venv/Lib/site-packages/requests_toolbelt-1.0.0.dist-info/top_level.txt
.venv/Lib/site-packages/rfc3986-2.0.0.dist-info/top_level.txt
.venv/Lib/site-packages/setuptools-68.2.0.dist-info/entry_points.txt
.venv/Lib/site-packages/setuptools-68.2.0.dist-info/top_level.txt
.venv/Lib/site-packages/twine-5.1.1.dist-info/entry_points.txt
.venv/Lib/site-packages/twine-5.1.1.dist-info/top_level.txt
.venv/Lib/site-packages/urllib3-2.2.2.dist-info/licenses/LICENSE.txt
.venv/Lib/site-packages/wheel-0.41.2.dist-info/LICENSE.txt
.venv/Lib/site-packages/wheel-0.41.2.dist-info/entry_points.txt
.venv/Lib/site-packages/zipp-3.20.0.dist-info/top_level.txt
DysonPythonHack.egg-info/PKG-INFO
DysonPythonHack.egg-info/SOURCES.txt
DysonPythonHack.egg-info/dependency_links.txt
DysonPythonHack.egg-info/requires.txt
DysonPythonHack.egg-info/top_level.txt