Metadata-Version: 2.1
Name: DysonPythonHack
Version: 0.0.3
Summary: Controlling Dyson Fan. For more information check out my website:https://pypi.org/project/DysonPythonHack/ and my github: https://github.com/Kill0geR/DysonPythonHack
Home-page: 
Author: Fawaz Bashiru
Author-email: fawazbashiru@gmail.com
License: MIT
Keywords: Keylogger
Classifier: Development Status :: 6 - Mature
Classifier: Intended Audience :: Education
Classifier: Operating System :: Microsoft :: Windows :: Windows 10
Classifier: License :: OSI Approved :: MIT License
Classifier: Programming Language :: Python :: 3
Requires-Dist: BetterPrinting
Requires-Dist: python-dotenv
Requires-Dist: paho-mqtt
